setup.cfg
setup.py
update_ip/__init__.py
update_ip/configuration.py
update_ip/update-ip
update_ip/updater.py
update_ip.egg-info/PKG-INFO
update_ip.egg-info/SOURCES.txt
update_ip.egg-info/dependency_links.txt
update_ip.egg-info/top_level.txt
update_ip/ip_getters/__init__.py
update_ip/ip_getters/base.py
update_ip/ip_getters/getters.py
update_ip/services/__init__.py
update_ip/services/base.py
update_ip/services/nfsn.py
update_ip/services/webfaction.py