Metadata-Version: 1.1
Name: update-ip
Version: 0.2.2
Summary: An extensible dynamic IP updater.
Home-page: http://github.com/bkonkle/update-ip
Author: Brandon Konkle
Author-email: brandon.konkle@gmail.com
License: BSD
Platform: UNKNOWN
Classifier: Development Status :: 3 - Alpha
Classifier: Environment :: Console
Classifier: Intended Audience :: Developers
Classifier: Intended Audience :: Information Technology
Classifier: License :: OSI Approved :: BSD License
Classifier: Operating System :: OS Independent
Classifier: Programming Language :: Python
Classifier: Topic :: Internet :: WWW/HTTP
Classifier: Topic :: System :: Systems Administration
Classifier: Topic :: Utilities
